sphinx_json_schema_formatter/__init__.py
sphinx_json_schema_formatter/directive.py
sphinx_json_schema_formatter/loader.py
sphinx_json_schema_formatter/mergers.py
tests/__init__.py
tests/test_allof.py
tests/test_merge.py
tests/test_not.py
tests/test_oneof.py
sphinx_json_schema_formatter-0.3.7.dist-info/LICENSE
sphinx_json_schema_formatter-0.3.7.dist-info/METADATA
sphinx_json_schema_formatter-0.3.7.dist-info/WHEEL
sphinx_json_schema_formatter-0.3.7.dist-info/top_level.txt
sphinx_json_schema_formatter-0.3.7.dist-info/zip-safe
sphinx_json_schema_formatter-0.3.7.dist-info/RECORD
