Metadata-Version: 2.1
Name: sphinx-json-schema-formatter
Version: 0.3.7
Summary: JSON Schema renderer for Sphinx
Home-page: https://github.com/tgallant/sphinx-json-schema-formatter
Author: Tim Gallant
Author-email: me@timgallant.us
License: UNKNOWN
Keywords: sphinx,json,schema
Platform: UNKNOWN
Classifier: Programming Language :: Python :: 3
Classifier: License :: OSI Approved :: MIT License
Classifier: Environment :: Plugins
Classifier: Framework :: Sphinx :: Extension
Classifier: Intended Audience :: Developers
Classifier: Topic :: Software Development :: Documentation
Classifier: Topic :: Documentation :: Sphinx
Requires-Dist: sphinx
Requires-Dist: jsonpointer
Requires-Dist: pyyaml
Provides-Extra: dev
Requires-Dist: black (==20.8b1) ; extra == 'dev'
Requires-Dist: bumpversion (==0.5.3) ; extra == 'dev'
Requires-Dist: twine (==3.4.2) ; extra == 'dev'
Requires-Dist: wheel (==0.37.0) ; extra == 'dev'
